encoding/__init__.py
iconvr/__init__.py
iconvr/__main__.py
iconvr-0.1.4.dist-info/DESCRIPTION.rst
iconvr-0.1.4.dist-info/METADATA
iconvr-0.1.4.dist-info/RECORD
iconvr-0.1.4.dist-info/WHEEL
iconvr-0.1.4.dist-info/metadata.json
iconvr-0.1.4.dist-info/top_level.txt
