Metadata-Version: 2.0
Name: iconvr
Version: 0.1.4
Summary: 文件编码转换工具
Home-page: https://github.com/zh5e/iconvr
Author: zh5e
Author-email: zhjie@live.com
License: UNKNOWN
Keywords: iconv,gbk,encoding
Platform: UNKNOWN
